{"team":"fk-zeleznicar-pancevo","stats":{"corners":"3.50","fouls":"16.08","goalKicks":"6.85","saves":"2.73","offsides":"1.46","shotsOnTarget":"3.96/3.73","yellowCards":"2.08/2.38","goals":"1.27/1.15","throwIns":"17.81","averageBallPossession":48.230769230769,"tackles":"12.69/13.19","interceptions":"9.35/8.69","aerialDuels":"15.58","aerialDuelsTotal":"28.35","dribbles":"7.58/7.92","dribblesTotal":"14.77/14.15"},"recentStats":{"corners":"3/6[H]+4/5[A]+4/5[H]+1/1[H]+6/1[A]+1/3[H]+0/6[A]+5/1[H]","fouls":"20/18[H]+11/12[A]+19/14[H]+14/19[H]+7/17[A]+21/25[H]+16/18[A]+17/13[H]","goalKicks":"11/2[H]+8/15[A]+8/5[H]+8/9[H]+3/6[A]+10/5[H]+10/8[A]+6/4[H]","saves":"1/3[H]+3/4[A]+5/3[H]+3/3[H]+1/1[A]+2/1[H]+9/1[A]+2/6[H]","offsides":"4/1[H]+1/1[A]+3/1[H]+0/2[H]+2/1[A]+1/0[H]+1/4[A]+4/1[H]","shotsOnTarget":"6/1[H]+4/4[A]+3/8[H]+4/4[H]+1/1[A]+1/2[H]+2/9[A]+12/2[H]","yellowCards":"2/4[H]+1/2[A]+2/1[H]+2/1[H]+1/2[A]+2/2[H]+1/4[A]+0/3[H]","goals":"3/0+1/1+1/3+1/1+0/0+0/0+1/1+6/0","throwIns":"16/16[H]+18/23[A]+8/9[H]+22/21[H]+23/34[A]+22/23[H]+13/22[A]+14/14[H]","averageBallPossession":"36/64[H]+67/33[A]+34/66[H]+54/46[H]+58/42[A]+37/63[H]+45/55[A]+56/44[H]","teams":"FK Železničar Pančevo,FK Tekstilac Odžaci,Home+FK Železničar Pančevo,FK Mladost Lučani,Away+FK Železničar Pančevo,FK Crvena zvezda,Home+FK Železničar Pančevo,FK Vojvodina,Home+FK Železničar Pančevo,FK Spartak Subotica,Away+FK Železničar Pančevo,FK Radnički Niš,Home+FK Železničar Pančevo,FK IMT Beograd,Away+FK Železničar Pančevo,FK Jedinstvo Ub,Home","tackles":"14/14[H]+10/10[A]+8/15[H]+16/22[H]+22/15[A]+9/16[H]+10/10[A]+5/11[H]","interceptions":"12/5[H]+5/12[A]+11/5[H]+8/8[H]+12/12[A]+11/11[H]+8/9[A]+12/8[H]","aerialDuels":"12/7[H]+16/18[A]+10/9[H]+21/22[H]+15/8[A]+22/17[H]+18/13[A]+19/12[H]","aerialDuelsTotal":"19/19+34/34+19/19+43/43+23/23+39/39+31/31+31/31","dribbles":"8/3[H]+12/6[A]+4/9[H]+11/11[H]+8/8[A]+6/7[H]+5/12[A]+5/10[H]","dribblesTotal":"14/11+17/13+12/11+21/23+12/18+13/10+11/19+11/13","cornersTotals":"24/28","cornersTotalsHome":"14/16","cornersTotalsAway":"10/12","cornersAverage":"3.00/3.50","cornersAverageHome":"2.80/3.20","cornersAverageAway":"3.33/4.00","foulsTotals":"125/136","foulsTotalsHome":"91/89","foulsTotalsAway":"34/47","foulsAverage":"15.63/17.00","foulsAverageHome":"18.20/17.80","foulsAverageAway":"11.33/15.67","goalKicksTotals":"64/54","goalKicksTotalsHome":"43/25","goalKicksTotalsAway":"21/29","goalKicksAverage":"8.00/6.75","goalKicksAverageHome":"8.60/5.00","goalKicksAverageAway":"7.00/9.67","savesTotals":"26/22","savesTotalsHome":"13/16","savesTotalsAway":"13/6","savesAverage":"3.25/2.75","savesAverageHome":"2.60/3.20","savesAverageAway":"4.33/2.00","offsidesTotals":"16/11","offsidesTotalsHome":"12/5","offsidesTotalsAway":"4/6","offsidesAverage":"2.00/1.38","offsidesAverageHome":"2.40/1.00","offsidesAverageAway":"1.33/2.00","shotsOnTargetTotals":"33/31","shotsOnTargetTotalsHome":"26/17","shotsOnTargetTotalsAway":"7/14","shotsOnTargetAverage":"4.13/3.88","shotsOnTargetAverageHome":"5.20/3.40","shotsOnTargetAverageAway":"2.33/4.67","yellowCardsTotals":"11/19","yellowCardsTotalsHome":"8/11","yellowCardsTotalsAway":"3/8","yellowCardsAverage":"1.38/2.38","yellowCardsAverageHome":"1.60/2.20","yellowCardsAverageAway":"1.00/2.67","goalsTotals":"13/6","goalsTotalsHome":"0/0","goalsTotalsAway":"13/6","goalsAverage":"1.63/0.75","goalsAverageHome":"NaN/NaN","goalsAverageAway":"1.63/0.75","throwInsTotals":"136/162","throwInsTotalsHome":"82/83","throwInsTotalsAway":"54/79","throwInsAverage":"17.00/20.25","throwInsAverageHome":"16.40/16.60","throwInsAverageAway":"18.00/26.33","averageBallPossessionTotals":"387/413","averageBallPossessionTotalsHome":"217/283","averageBallPossessionTotalsAway":"170/130","averageBallPossessionAverage":"48.38/51.63","averageBallPossessionAverageHome":"43.40/56.60","averageBallPossessionAverageAway":"56.67/43.33","tacklesTotals":"94/113","tacklesTotalsHome":"52/78","tacklesTotalsAway":"42/35","tacklesAverage":"11.75/14.13","tacklesAverageHome":"10.40/15.60","tacklesAverageAway":"14.00/11.67","interceptionsTotals":"79/70","interceptionsTotalsHome":"54/37","interceptionsTotalsAway":"25/33","interceptionsAverage":"9.88/8.75","interceptionsAverageHome":"10.80/7.40","interceptionsAverageAway":"8.33/11.00","aerialDuelsTotals":"133/106","aerialDuelsTotalsHome":"84/67","aerialDuelsTotalsAway":"49/39","aerialDuelsAverage":"16.63/13.25","aerialDuelsAverageHome":"16.80/13.40","aerialDuelsAverageAway":"16.33/13.00","aerialDuelsTotalTotals":"239/239","aerialDuelsTotalTotalsHome":"0/0","aerialDuelsTotalTotalsAway":"239/239","aerialDuelsTotalAverage":"29.88/29.88","aerialDuelsTotalAverageHome":"NaN/NaN","aerialDuelsTotalAverageAway":"29.88/29.88","dribblesTotals":"59/66","dribblesTotalsHome":"34/40","dribblesTotalsAway":"25/26","dribblesAverage":"7.38/8.25","dribblesAverageHome":"6.80/8.00","dribblesAverageAway":"8.33/8.67","dribblesTotalTotals":"111/118","dribblesTotalTotalsHome":"0/0","dribblesTotalTotalsAway":"111/118","dribblesTotalAverage":"13.88/14.75","dribblesTotalAverageHome":"NaN/NaN","dribblesTotalAverageAway":"13.88/14.75"}}