{
    "globalStatistics": {
        "corners": "4.63",
        "fouls": "13.79",
        "goalKicks": "8.95",
        "saves": "3.05",
        "offsides": "1.53",
        "shotsOnTarget": "3.79/4.47",
        "yellowCards": "2.58/2.79",
        "goals": "1.26/1.26",
        "throwIns": "18.79",
        "ballPossession": 49.578947368421,
        "tackles": "13.47/15.37",
        "interceptions": "8.89/9.84",
        "aerialDuels": "16.84",
        "aerialDuelsAttempted": "34.11",
        "dribbles": "7.68/6.00",
        "dribblesAttempted": "15.68/12.32"
    },
    "teamSlug": "holstein-kiel",
    "teamId": "2573",
    "teamName": "Holstein Kiel",
    "tournament": "2. Bundesliga",
    "matchLinks": [
        {
            "href": "https://www.sofascore.com/football/match/holstein-kiel-arminia-bielefeld/Pabsybb#id:14065419,tab:statistics",
            "teams": [
                "Bielefeld",
                "Kiel"
            ],
            "goals": [
                "2",
                "2"
            ],
            "teamIds": [
                "2540",
                "2573"
            ],
            "isHome": false
        },
        {
            "href": "https://www.sofascore.com/football/match/holstein-kiel-sc-paderborn-07/lbbsybb#id:14065402,tab:statistics",
            "teams": [
                "Kiel",
                "Paderborn"
            ],
            "goals": [
                "2",
                "0"
            ],
            "teamIds": [
                "2573",
                "2561"
            ],
            "isHome": true
        },
        {
            "href": "https://www.sofascore.com/football/match/sg-dynamo-dresden-holstein-kiel/ybbsVbb#id:14065392,tab:statistics",
            "teams": [
                "Kiel",
                "Dresden"
            ],
            "goals": [
                "2",
                "1"
            ],
            "teamIds": [
                "2573",
                "2595"
            ],
            "isHome": true
        },
        {
            "href": "https://www.sofascore.com/football/match/1-fc-magdeburg-holstein-kiel/ybbsQbb#id:14065386,tab:statistics",
            "teams": [
                "Magdeburg",
                "Kiel"
            ],
            "goals": [
                "3",
                "3"
            ],
            "teamIds": [
                "2591",
                "2573"
            ],
            "isHome": false
        },
        {
            "href": "https://www.sofascore.com/football/match/holstein-kiel-eintracht-braunschweig/hbbsybb#id:14065382,tab:statistics",
            "teams": [
                "Braunschweig",
                "Kiel"
            ],
            "goals": [
                "1",
                "1"
            ],
            "teamIds": [
                "2557",
                "2573"
            ],
            "isHome": false
        },
        {
            "href": "https://www.sofascore.com/football/match/holstein-kiel-hertha-bsc/Dabsybb#id:14065365,tab:statistics",
            "teams": [
                "Kiel",
                "Hertha"
            ],
            "goals": [
                "0",
                "1"
            ],
            "teamIds": [
                "2573",
                "2528"
            ],
            "isHome": true
        },
        {
            "href": "https://www.sofascore.com/football/match/1-fc-kaiserslautern-holstein-kiel/ybbsAdb#id:14065359,tab:statistics",
            "teams": [
                "Kaiserslautern",
                "Kiel"
            ],
            "goals": [
                "4",
                "1"
            ],
            "teamIds": [
                "2675",
                "2573"
            ],
            "isHome": false
        },
        {
            "href": "https://www.sofascore.com/football/match/fortuna-dusseldorf-holstein-kiel/ybbsNbb#id:14065348,tab:statistics",
            "teams": [
                "Kiel",
                "Fortuna"
            ],
            "goals": [
                "1",
                "0"
            ],
            "teamIds": [
                "2573",
                "2588"
            ],
            "isHome": true
        }
    ],
    "homeMatchCount": 4,
    "awayMatchCount": 4,
    "matchStatistics": [
        {
            "corners": "6/5[A]",
            "fouls": "16/10[A]",
            "goalKicks": "12/4[A]",
            "saves": "3/0[A]",
            "offsides": "1/1[A]",
            "shotsOnTarget": "1/5[A]",
            "yellowCards": "3/1[A]",
            "goals": "2/2[A]",
            "throwIns": "17/18[A]",
            "averageBallPossession": "38/62[A]",
            "teams": "Kiel,Bielefeld,Away",
            "tackles": "11/21[A]",
            "interceptions": "7/5[A]",
            "aerialDuels": "29/28[A]",
            "aerialDuelsAttempted": "57/57[A]",
            "dribbles": "8/5[A]",
            "dribblesAttempted": "15/9[A]",
            "isHome": false
        },
        {
            "corners": "1/11[H]",
            "fouls": "12/18[H]",
            "goalKicks": "9/3[H]",
            "saves": "4/1[H]",
            "offsides": "0/4[H]",
            "shotsOnTarget": "3/4[H]",
            "yellowCards": "3/3[H]",
            "goals": "2/0[H]",
            "throwIns": "15/27[H]",
            "averageBallPossession": "38/62[H]",
            "teams": "Kiel,Paderborn,Home",
            "tackles": "12/16[H]",
            "interceptions": "11/15[H]",
            "aerialDuels": "13/20[H]",
            "aerialDuelsAttempted": "33/33[H]",
            "dribbles": "6/6[H]",
            "dribblesAttempted": "14/12[H]",
            "isHome": true
        },
        {
            "corners": "7/9[H]",
            "fouls": "7/8[H]",
            "goalKicks": "8/5[H]",
            "saves": "7/2[H]",
            "offsides": "1/0[H]",
            "shotsOnTarget": "4/8[H]",
            "yellowCards": "0/1[H]",
            "goals": "2/1[H]",
            "throwIns": "17/21[H]",
            "averageBallPossession": "49/51[H]",
            "teams": "Kiel,Dresden,Home",
            "tackles": "13/10[H]",
            "interceptions": "7/16[H]",
            "aerialDuels": "20/28[H]",
            "aerialDuelsAttempted": "48/48[H]",
            "dribbles": "6/5[H]",
            "dribblesAttempted": "10/11[H]",
            "isHome": true
        },
        {
            "corners": "4/6[A]",
            "fouls": "14/11[A]",
            "goalKicks": "10/8[A]",
            "saves": "5/3[A]",
            "offsides": "1/3[A]",
            "shotsOnTarget": "6/8[A]",
            "yellowCards": "3/2[A]",
            "goals": "3/3[A]",
            "throwIns": "22/16[A]",
            "averageBallPossession": "42/58[A]",
            "teams": "Kiel,Magdeburg,Away",
            "tackles": "11/14[A]",
            "interceptions": "8/12[A]",
            "aerialDuels": "14/15[A]",
            "aerialDuelsAttempted": "29/29[A]",
            "dribbles": "6/5[A]",
            "dribblesAttempted": "18/13[A]",
            "isHome": false
        },
        {
            "corners": "4/2[A]",
            "fouls": "17/13[A]",
            "goalKicks": "10/10[A]",
            "saves": "2/1[A]",
            "offsides": "3/2[A]",
            "shotsOnTarget": "2/3[A]",
            "yellowCards": "5/1[A]",
            "goals": "1/1[A]",
            "throwIns": "13/23[A]",
            "averageBallPossession": "63/37[A]",
            "teams": "Kiel,Braunschweig,Away",
            "tackles": "17/12[A]",
            "interceptions": "8/6[A]",
            "aerialDuels": "17/15[A]",
            "aerialDuelsAttempted": "32/32[A]",
            "dribbles": "8/10[A]",
            "dribblesAttempted": "16/20[A]",
            "isHome": false
        },
        {
            "corners": "8/3[H]",
            "fouls": "13/14[H]",
            "goalKicks": "9/9[H]",
            "saves": "1/0[H]",
            "offsides": "2/2[H]",
            "shotsOnTarget": "0/2[H]",
            "yellowCards": "2/6[H]",
            "goals": "0/1[H]",
            "throwIns": "16/27[H]",
            "averageBallPossession": "52/48[H]",
            "teams": "Kiel,Hertha,Home",
            "tackles": "15/18[H]",
            "interceptions": "9/11[H]",
            "aerialDuels": "18/13[H]",
            "aerialDuelsAttempted": "31/31[H]",
            "dribbles": "8/3[H]",
            "dribblesAttempted": "18/12[H]",
            "isHome": true
        },
        {
            "corners": "3/10[A]",
            "fouls": "16/14[A]",
            "goalKicks": "11/9[A]",
            "saves": "6/1[A]",
            "offsides": "0/2[A]",
            "shotsOnTarget": "2/10[A]",
            "yellowCards": "5/2[A]",
            "goals": "1/4[A]",
            "throwIns": "19/24[A]",
            "averageBallPossession": "37/63[A]",
            "teams": "Kiel,Kaiserslautern,Away",
            "tackles": "19/23[A]",
            "interceptions": "5/16[A]",
            "aerialDuels": "14/19[A]",
            "aerialDuelsAttempted": "33/33[A]",
            "dribbles": "7/8[A]",
            "dribblesAttempted": "18/15[A]",
            "isHome": false
        },
        {
            "corners": "3/5[H]",
            "fouls": "9/16[H]",
            "goalKicks": "9/6[H]",
            "saves": "6/3[H]",
            "offsides": "2/1[H]",
            "shotsOnTarget": "4/6[H]",
            "yellowCards": "1/3[H]",
            "goals": "1/0[H]",
            "throwIns": "20/24[H]",
            "averageBallPossession": "44/56[H]",
            "teams": "Kiel,Fortuna,Home",
            "tackles": "21/18[H]",
            "interceptions": "9/9[H]",
            "aerialDuels": "14/30[H]",
            "aerialDuelsAttempted": "44/44[H]",
            "dribbles": "11/8[H]",
            "dribblesAttempted": "21/16[H]",
            "isHome": true
        }
    ],
    "attempts": 0,
    "startTime": "2026-01-31T12:33:16.207Z",
    "endTime": "2026-01-31T12:33:50.956Z",
    "totalTimeSeconds": 34.75,
    "combinedMatchStatistics": {
        "corners": "6/5[A]+1/11[H]+7/9[H]+4/6[A]+4/2[A]+8/3[H]+3/10[A]+3/5[H]",
        "fouls": "16/10[A]+12/18[H]+7/8[H]+14/11[A]+17/13[A]+13/14[H]+16/14[A]+9/16[H]",
        "goalKicks": "12/4[A]+9/3[H]+8/5[H]+10/8[A]+10/10[A]+9/9[H]+11/9[A]+9/6[H]",
        "saves": "3/0[A]+4/1[H]+7/2[H]+5/3[A]+2/1[A]+1/0[H]+6/1[A]+6/3[H]",
        "offsides": "1/1[A]+0/4[H]+1/0[H]+1/3[A]+3/2[A]+2/2[H]+0/2[A]+2/1[H]",
        "shotsOnTarget": "1/5[A]+3/4[H]+4/8[H]+6/8[A]+2/3[A]+0/2[H]+2/10[A]+4/6[H]",
        "yellowCards": "3/1[A]+3/3[H]+0/1[H]+3/2[A]+5/1[A]+2/6[H]+5/2[A]+1/3[H]",
        "goals": "2/2[A]+2/0[H]+2/1[H]+3/3[A]+1/1[A]+0/1[H]+1/4[A]+1/0[H]",
        "throwIns": "17/18[A]+15/27[H]+17/21[H]+22/16[A]+13/23[A]+16/27[H]+19/24[A]+20/24[H]",
        "averageBallPossession": "38/62[A]+38/62[H]+49/51[H]+42/58[A]+63/37[A]+52/48[H]+37/63[A]+44/56[H]",
        "teams": "Kiel,Bielefeld,Away+Kiel,Paderborn,Home+Kiel,Dresden,Home+Kiel,Magdeburg,Away+Kiel,Braunschweig,Away+Kiel,Hertha,Home+Kiel,Kaiserslautern,Away+Kiel,Fortuna,Home",
        "tackles": "11/21[A]+12/16[H]+13/10[H]+11/14[A]+17/12[A]+15/18[H]+19/23[A]+21/18[H]",
        "interceptions": "7/5[A]+11/15[H]+7/16[H]+8/12[A]+8/6[A]+9/11[H]+5/16[A]+9/9[H]",
        "aerialDuels": "29/28[A]+13/20[H]+20/28[H]+14/15[A]+17/15[A]+18/13[H]+14/19[A]+14/30[H]",
        "aerialDuelsAttempted": "57/57[A]+33/33[H]+48/48[H]+29/29[A]+32/32[A]+31/31[H]+33/33[A]+44/44[H]",
        "dribbles": "8/5[A]+6/6[H]+6/5[H]+6/5[A]+8/10[A]+8/3[H]+7/8[A]+11/8[H]",
        "dribblesAttempted": "15/9[A]+14/12[H]+10/11[H]+18/13[A]+16/20[A]+18/12[H]+18/15[A]+21/16[H]",
        "isHome": "false+true+true+false+false+true+false+true",
        "cornersTotals": "36/51",
        "cornersTotalsHome": "19/28",
        "cornersTotalsAway": "17/23",
        "cornersAverage": "4.50/6.38",
        "cornersAverageHome": "4.75/7.00",
        "cornersAverageAway": "4.25/5.75",
        "foulsTotals": "104/104",
        "foulsTotalsHome": "41/56",
        "foulsTotalsAway": "63/48",
        "foulsAverage": "13.00/13.00",
        "foulsAverageHome": "10.25/14.00",
        "foulsAverageAway": "15.75/12.00",
        "goalKicksTotals": "78/54",
        "goalKicksTotalsHome": "35/23",
        "goalKicksTotalsAway": "43/31",
        "goalKicksAverage": "9.75/6.75",
        "goalKicksAverageHome": "8.75/5.75",
        "goalKicksAverageAway": "10.75/7.75",
        "savesTotals": "34/11",
        "savesTotalsHome": "18/6",
        "savesTotalsAway": "16/5",
        "savesAverage": "4.25/1.38",
        "savesAverageHome": "4.50/1.50",
        "savesAverageAway": "4.00/1.25",
        "offsidesTotals": "10/15",
        "offsidesTotalsHome": "5/7",
        "offsidesTotalsAway": "5/8",
        "offsidesAverage": "1.25/1.88",
        "offsidesAverageHome": "1.25/1.75",
        "offsidesAverageAway": "1.25/2.00",
        "shotsOnTargetTotals": "22/46",
        "shotsOnTargetTotalsHome": "11/20",
        "shotsOnTargetTotalsAway": "11/26",
        "shotsOnTargetAverage": "2.75/5.75",
        "shotsOnTargetAverageHome": "2.75/5.00",
        "shotsOnTargetAverageAway": "2.75/6.50",
        "yellowCardsTotals": "22/19",
        "yellowCardsTotalsHome": "6/13",
        "yellowCardsTotalsAway": "16/6",
        "yellowCardsAverage": "2.75/2.38",
        "yellowCardsAverageHome": "1.50/3.25",
        "yellowCardsAverageAway": "4.00/1.50",
        "goalsTotals": "12/12",
        "goalsTotalsHome": "5/2",
        "goalsTotalsAway": "7/10",
        "goalsAverage": "1.50/1.50",
        "goalsAverageHome": "1.25/0.50",
        "goalsAverageAway": "1.75/2.50",
        "throwInsTotals": "139/180",
        "throwInsTotalsHome": "68/99",
        "throwInsTotalsAway": "71/81",
        "throwInsAverage": "17.38/22.50",
        "throwInsAverageHome": "17.00/24.75",
        "throwInsAverageAway": "17.75/20.25",
        "averageBallPossessionTotals": "363/437",
        "averageBallPossessionTotalsHome": "183/217",
        "averageBallPossessionTotalsAway": "180/220",
        "averageBallPossessionAverage": "45.38/54.63",
        "averageBallPossessionAverageHome": "45.75/54.25",
        "averageBallPossessionAverageAway": "45.00/55.00",
        "tacklesTotals": "119/132",
        "tacklesTotalsHome": "61/62",
        "tacklesTotalsAway": "58/70",
        "tacklesAverage": "14.88/16.50",
        "tacklesAverageHome": "15.25/15.50",
        "tacklesAverageAway": "14.50/17.50",
        "interceptionsTotals": "64/90",
        "interceptionsTotalsHome": "36/51",
        "interceptionsTotalsAway": "28/39",
        "interceptionsAverage": "8.00/11.25",
        "interceptionsAverageHome": "9.00/12.75",
        "interceptionsAverageAway": "7.00/9.75",
        "aerialDuelsTotals": "139/168",
        "aerialDuelsTotalsHome": "65/91",
        "aerialDuelsTotalsAway": "74/77",
        "aerialDuelsAverage": "17.38/21.00",
        "aerialDuelsAverageHome": "16.25/22.75",
        "aerialDuelsAverageAway": "18.50/19.25",
        "aerialDuelsAttemptedTotals": "307/307",
        "aerialDuelsAttemptedTotalsHome": "156/156",
        "aerialDuelsAttemptedTotalsAway": "151/151",
        "aerialDuelsAttemptedAverage": "38.38/38.38",
        "aerialDuelsAttemptedAverageHome": "39.00/39.00",
        "aerialDuelsAttemptedAverageAway": "37.75/37.75",
        "dribblesTotals": "60/50",
        "dribblesTotalsHome": "31/22",
        "dribblesTotalsAway": "29/28",
        "dribblesAverage": "7.50/6.25",
        "dribblesAverageHome": "7.75/5.50",
        "dribblesAverageAway": "7.25/7.00",
        "dribblesAttemptedTotals": "130/108",
        "dribblesAttemptedTotalsHome": "63/51",
        "dribblesAttemptedTotalsAway": "67/57",
        "dribblesAttemptedAverage": "16.25/13.50",
        "dribblesAttemptedAverageHome": "15.75/12.75",
        "dribblesAttemptedAverageAway": "16.75/14.25"
    }
}