{
    "globalStatistics": {
        "corners": "5.35",
        "fouls": "10.70",
        "goalKicks": "7.78",
        "saves": "2.61",
        "offsides": "1.35",
        "shotsOnTarget": "3.78/4.13",
        "yellowCards": "1.52/1.83",
        "goals": "1.00/1.48",
        "throwIns": "19.35",
        "ballPossession": 48.695652173913,
        "tackles": "17.13/16.91",
        "interceptions": "7.83/8.83",
        "aerialDuels": "14.43",
        "aerialDuelsAttempted": "30.91",
        "dribbles": "7.13/7.61",
        "dribblesAttempted": "15.48/16.48"
    },
    "teamSlug": "nottingham-forest",
    "teamId": "14",
    "teamName": "Nottingham Forest",
    "tournament": "Premier League",
    "matchLinks": [
        {
            "href": "https://www.sofascore.com/football/match/brentford-nottingham-forest/osab#id:14025101,tab:statistics",
            "teams": [
                "Brentford",
                "Forest"
            ],
            "goals": [
                "0",
                "2"
            ],
            "teamIds": [
                "50",
                "14"
            ],
            "isHome": false
        },
        {
            "href": "https://www.sofascore.com/football/match/arsenal-nottingham-forest/osR#id:14025082,tab:statistics",
            "teams": [
                "Forest",
                "Arsenal"
            ],
            "goals": [
                "0",
                "0"
            ],
            "teamIds": [
                "14",
                "42"
            ],
            "isHome": true
        },
        {
            "href": "https://www.sofascore.com/football/match/west-ham-united-nottingham-forest/osM#id:14025055,tab:statistics",
            "teams": [
                "West Ham",
                "Forest"
            ],
            "goals": [
                "1",
                "2"
            ],
            "teamIds": [
                "37",
                "14"
            ],
            "isHome": false
        },
        {
            "href": "https://www.sofascore.com/football/match/aston-villa-nottingham-forest/osP#id:14025276,tab:statistics",
            "teams": [
                "Aston Villa",
                "Forest"
            ],
            "goals": [
                "3",
                "1"
            ],
            "teamIds": [
                "40",
                "14"
            ],
            "isHome": false
        },
        {
            "href": "https://www.sofascore.com/football/match/everton-nottingham-forest/osY#id:14025268,tab:statistics",
            "teams": [
                "Forest",
                "Everton"
            ],
            "goals": [
                "0",
                "2"
            ],
            "teamIds": [
                "14",
                "48"
            ],
            "isHome": true
        },
        {
            "href": "https://www.sofascore.com/football/match/manchester-city-nottingham-forest/osr#id:14025248,tab:statistics",
            "teams": [
                "Forest",
                "Man City"
            ],
            "goals": [
                "1",
                "2"
            ],
            "teamIds": [
                "14",
                "17"
            ],
            "isHome": true
        },
        {
            "href": "https://www.sofascore.com/football/match/fulham-nottingham-forest/osT#id:14907281,tab:statistics",
            "teams": [
                "Fulham",
                "Forest"
            ],
            "goals": [
                "1",
                "0"
            ],
            "teamIds": [
                "43",
                "14"
            ],
            "isHome": false
        },
        {
            "href": "https://www.sofascore.com/football/match/tottenham-hotspur-nottingham-forest/osI#id:14025204,tab:statistics",
            "teams": [
                "Forest",
                "Tottenham"
            ],
            "goals": [
                "3",
                "0"
            ],
            "teamIds": [
                "14",
                "33"
            ],
            "isHome": true
        }
    ],
    "homeMatchCount": 4,
    "awayMatchCount": 4,
    "matchStatistics": [
        {
            "corners": "5/6[A]",
            "fouls": "10/11[A]",
            "goalKicks": "11/5[A]",
            "saves": "1/0[A]",
            "offsides": "0/1[A]",
            "shotsOnTarget": "2/1[A]",
            "yellowCards": "0/1[A]",
            "goals": "2/0[A]",
            "throwIns": "14/24[A]",
            "averageBallPossession": "34/66[A]",
            "teams": "Forest,Brentford,Away",
            "tackles": "18/14[A]",
            "interceptions": "8/15[A]",
            "aerialDuels": "16/23[A]",
            "aerialDuelsAttempted": "39/39[A]",
            "dribbles": "9/10[A]",
            "dribblesAttempted": "15/19[A]",
            "isHome": false
        },
        {
            "corners": "4/9[H]",
            "fouls": "8/14[H]",
            "goalKicks": "11/6[H]",
            "saves": "3/0[H]",
            "offsides": "1/0[H]",
            "shotsOnTarget": "0/3[H]",
            "yellowCards": "1/1[H]",
            "goals": "0/0[H]",
            "throwIns": "19/10[H]",
            "averageBallPossession": "40/60[H]",
            "teams": "Forest,Arsenal,Home",
            "tackles": "12/16[H]",
            "interceptions": "6/4[H]",
            "aerialDuels": "17/18[H]",
            "aerialDuelsAttempted": "35/35[H]",
            "dribbles": "4/6[H]",
            "dribblesAttempted": "14/13[H]",
            "isHome": true
        },
        {
            "corners": "5/6[A]",
            "fouls": "9/15[A]",
            "goalKicks": "5/6[A]",
            "saves": "3/3[A]",
            "offsides": "0/1[A]",
            "shotsOnTarget": "5/3[A]",
            "yellowCards": "0/3[A]",
            "goals": "2/1[A]",
            "throwIns": "27/23[A]",
            "averageBallPossession": "53/47[A]",
            "teams": "Forest,West Ham,Away",
            "tackles": "15/28[A]",
            "interceptions": "6/7[A]",
            "aerialDuels": "21/27[A]",
            "aerialDuelsAttempted": "48/48[A]",
            "dribbles": "2/2[A]",
            "dribblesAttempted": "16/8[A]",
            "isHome": false
        },
        {
            "corners": "4/4[A]",
            "fouls": "20/10[A]",
            "goalKicks": "11/4[A]",
            "saves": "1/4[A]",
            "offsides": "4/1[A]",
            "shotsOnTarget": "5/4[A]",
            "yellowCards": "2/1[A]",
            "goals": "1/3[A]",
            "throwIns": "8/17[A]",
            "averageBallPossession": "27/73[A]",
            "teams": "Forest,Aston Villa,Away",
            "tackles": "19/18[A]",
            "interceptions": "14/11[A]",
            "aerialDuels": "6/10[A]",
            "aerialDuelsAttempted": "16/16[A]",
            "dribbles": "8/4[A]",
            "dribblesAttempted": "10/15[A]",
            "isHome": false
        },
        {
            "corners": "9/2[H]",
            "fouls": "11/9[H]",
            "goalKicks": "5/13[H]",
            "saves": "1/6[H]",
            "offsides": "0/0[H]",
            "shotsOnTarget": "6/3[H]",
            "yellowCards": "1/0[H]",
            "goals": "0/2[H]",
            "throwIns": "23/14[H]",
            "averageBallPossession": "70/30[H]",
            "teams": "Forest,Everton,Home",
            "tackles": "21/23[H]",
            "interceptions": "5/9[H]",
            "aerialDuels": "13/25[H]",
            "aerialDuelsAttempted": "38/38[H]",
            "dribbles": "16/7[H]",
            "dribblesAttempted": "25/15[H]",
            "isHome": true
        },
        {
            "corners": "5/5[H]",
            "fouls": "5/13[H]",
            "goalKicks": "8/7[H]",
            "saves": "3/1[H]",
            "offsides": "1/1[H]",
            "shotsOnTarget": "2/5[H]",
            "yellowCards": "1/2[H]",
            "goals": "1/2[H]",
            "throwIns": "17/16[H]",
            "averageBallPossession": "34/66[H]",
            "teams": "Forest,Man City,Home",
            "tackles": "15/14[H]",
            "interceptions": "8/4[H]",
            "aerialDuels": "12/13[H]",
            "aerialDuelsAttempted": "25/25[H]",
            "dribbles": "6/11[H]",
            "dribblesAttempted": "17/21[H]",
            "isHome": true
        },
        {
            "corners": "5/1[A]",
            "fouls": "9/5[A]",
            "goalKicks": "7/9[A]",
            "saves": "0/2[A]",
            "offsides": "2/2[A]",
            "shotsOnTarget": "2/1[A]",
            "yellowCards": "4/5[A]",
            "goals": "0/1[A]",
            "throwIns": "22/18[A]",
            "averageBallPossession": "50/50[A]",
            "teams": "Forest,Fulham,Away",
            "tackles": "10/21[A]",
            "interceptions": "8/10[A]",
            "aerialDuels": "17/17[A]",
            "aerialDuelsAttempted": "34/34[A]",
            "dribbles": "3/8[A]",
            "dribblesAttempted": "16/12[A]",
            "isHome": false
        },
        {
            "corners": "3/3[H]",
            "fouls": "9/13[H]",
            "goalKicks": "6/9[H]",
            "saves": "1/3[H]",
            "offsides": "4/1[H]",
            "shotsOnTarget": "6/1[H]",
            "yellowCards": "1/3[H]",
            "goals": "3/0[H]",
            "throwIns": "22/24[H]",
            "averageBallPossession": "48/52[H]",
            "teams": "Forest,Tottenham,Home",
            "tackles": "17/30[H]",
            "interceptions": "12/11[H]",
            "aerialDuels": "13/10[H]",
            "aerialDuelsAttempted": "23/23[H]",
            "dribbles": "6/12[H]",
            "dribblesAttempted": "17/21[H]",
            "isHome": true
        }
    ],
    "attempts": 0,
    "startTime": "2026-01-31T17:24:44.135Z",
    "endTime": "2026-01-31T17:25:11.927Z",
    "totalTimeSeconds": 27.79,
    "combinedMatchStatistics": {
        "corners": "5/6[A]+4/9[H]+5/6[A]+4/4[A]+9/2[H]+5/5[H]+5/1[A]+3/3[H]",
        "fouls": "10/11[A]+8/14[H]+9/15[A]+20/10[A]+11/9[H]+5/13[H]+9/5[A]+9/13[H]",
        "goalKicks": "11/5[A]+11/6[H]+5/6[A]+11/4[A]+5/13[H]+8/7[H]+7/9[A]+6/9[H]",
        "saves": "1/0[A]+3/0[H]+3/3[A]+1/4[A]+1/6[H]+3/1[H]+0/2[A]+1/3[H]",
        "offsides": "0/1[A]+1/0[H]+0/1[A]+4/1[A]+0/0[H]+1/1[H]+2/2[A]+4/1[H]",
        "shotsOnTarget": "2/1[A]+0/3[H]+5/3[A]+5/4[A]+6/3[H]+2/5[H]+2/1[A]+6/1[H]",
        "yellowCards": "0/1[A]+1/1[H]+0/3[A]+2/1[A]+1/0[H]+1/2[H]+4/5[A]+1/3[H]",
        "goals": "2/0[A]+0/0[H]+2/1[A]+1/3[A]+0/2[H]+1/2[H]+0/1[A]+3/0[H]",
        "throwIns": "14/24[A]+19/10[H]+27/23[A]+8/17[A]+23/14[H]+17/16[H]+22/18[A]+22/24[H]",
        "averageBallPossession": "34/66[A]+40/60[H]+53/47[A]+27/73[A]+70/30[H]+34/66[H]+50/50[A]+48/52[H]",
        "teams": "Forest,Brentford,Away+Forest,Arsenal,Home+Forest,West Ham,Away+Forest,Aston Villa,Away+Forest,Everton,Home+Forest,Man City,Home+Forest,Fulham,Away+Forest,Tottenham,Home",
        "tackles": "18/14[A]+12/16[H]+15/28[A]+19/18[A]+21/23[H]+15/14[H]+10/21[A]+17/30[H]",
        "interceptions": "8/15[A]+6/4[H]+6/7[A]+14/11[A]+5/9[H]+8/4[H]+8/10[A]+12/11[H]",
        "aerialDuels": "16/23[A]+17/18[H]+21/27[A]+6/10[A]+13/25[H]+12/13[H]+17/17[A]+13/10[H]",
        "aerialDuelsAttempted": "39/39[A]+35/35[H]+48/48[A]+16/16[A]+38/38[H]+25/25[H]+34/34[A]+23/23[H]",
        "dribbles": "9/10[A]+4/6[H]+2/2[A]+8/4[A]+16/7[H]+6/11[H]+3/8[A]+6/12[H]",
        "dribblesAttempted": "15/19[A]+14/13[H]+16/8[A]+10/15[A]+25/15[H]+17/21[H]+16/12[A]+17/21[H]",
        "isHome": "false+true+false+false+true+true+false+true",
        "cornersTotals": "40/36",
        "cornersTotalsHome": "21/19",
        "cornersTotalsAway": "19/17",
        "cornersAverage": "5.00/4.50",
        "cornersAverageHome": "5.25/4.75",
        "cornersAverageAway": "4.75/4.25",
        "foulsTotals": "81/90",
        "foulsTotalsHome": "33/49",
        "foulsTotalsAway": "48/41",
        "foulsAverage": "10.13/11.25",
        "foulsAverageHome": "8.25/12.25",
        "foulsAverageAway": "12.00/10.25",
        "goalKicksTotals": "64/59",
        "goalKicksTotalsHome": "30/35",
        "goalKicksTotalsAway": "34/24",
        "goalKicksAverage": "8.00/7.38",
        "goalKicksAverageHome": "7.50/8.75",
        "goalKicksAverageAway": "8.50/6.00",
        "savesTotals": "13/19",
        "savesTotalsHome": "8/10",
        "savesTotalsAway": "5/9",
        "savesAverage": "1.63/2.38",
        "savesAverageHome": "2.00/2.50",
        "savesAverageAway": "1.25/2.25",
        "offsidesTotals": "12/7",
        "offsidesTotalsHome": "6/2",
        "offsidesTotalsAway": "6/5",
        "offsidesAverage": "1.50/0.88",
        "offsidesAverageHome": "1.50/0.50",
        "offsidesAverageAway": "1.50/1.25",
        "shotsOnTargetTotals": "28/21",
        "shotsOnTargetTotalsHome": "14/12",
        "shotsOnTargetTotalsAway": "14/9",
        "shotsOnTargetAverage": "3.50/2.63",
        "shotsOnTargetAverageHome": "3.50/3.00",
        "shotsOnTargetAverageAway": "3.50/2.25",
        "yellowCardsTotals": "10/16",
        "yellowCardsTotalsHome": "4/6",
        "yellowCardsTotalsAway": "6/10",
        "yellowCardsAverage": "1.25/2.00",
        "yellowCardsAverageHome": "1.00/1.50",
        "yellowCardsAverageAway": "1.50/2.50",
        "goalsTotals": "9/9",
        "goalsTotalsHome": "4/4",
        "goalsTotalsAway": "5/5",
        "goalsAverage": "1.13/1.13",
        "goalsAverageHome": "1.00/1.00",
        "goalsAverageAway": "1.25/1.25",
        "throwInsTotals": "152/146",
        "throwInsTotalsHome": "81/64",
        "throwInsTotalsAway": "71/82",
        "throwInsAverage": "19.00/18.25",
        "throwInsAverageHome": "20.25/16.00",
        "throwInsAverageAway": "17.75/20.50",
        "averageBallPossessionTotals": "356/444",
        "averageBallPossessionTotalsHome": "192/208",
        "averageBallPossessionTotalsAway": "164/236",
        "averageBallPossessionAverage": "44.50/55.50",
        "averageBallPossessionAverageHome": "48.00/52.00",
        "averageBallPossessionAverageAway": "41.00/59.00",
        "tacklesTotals": "127/164",
        "tacklesTotalsHome": "65/83",
        "tacklesTotalsAway": "62/81",
        "tacklesAverage": "15.88/20.50",
        "tacklesAverageHome": "16.25/20.75",
        "tacklesAverageAway": "15.50/20.25",
        "interceptionsTotals": "67/71",
        "interceptionsTotalsHome": "31/28",
        "interceptionsTotalsAway": "36/43",
        "interceptionsAverage": "8.38/8.88",
        "interceptionsAverageHome": "7.75/7.00",
        "interceptionsAverageAway": "9.00/10.75",
        "aerialDuelsTotals": "115/143",
        "aerialDuelsTotalsHome": "55/66",
        "aerialDuelsTotalsAway": "60/77",
        "aerialDuelsAverage": "14.38/17.88",
        "aerialDuelsAverageHome": "13.75/16.50",
        "aerialDuelsAverageAway": "15.00/19.25",
        "aerialDuelsAttemptedTotals": "258/258",
        "aerialDuelsAttemptedTotalsHome": "121/121",
        "aerialDuelsAttemptedTotalsAway": "137/137",
        "aerialDuelsAttemptedAverage": "32.25/32.25",
        "aerialDuelsAttemptedAverageHome": "30.25/30.25",
        "aerialDuelsAttemptedAverageAway": "34.25/34.25",
        "dribblesTotals": "54/60",
        "dribblesTotalsHome": "32/36",
        "dribblesTotalsAway": "22/24",
        "dribblesAverage": "6.75/7.50",
        "dribblesAverageHome": "8.00/9.00",
        "dribblesAverageAway": "5.50/6.00",
        "dribblesAttemptedTotals": "130/124",
        "dribblesAttemptedTotalsHome": "73/70",
        "dribblesAttemptedTotalsAway": "57/54",
        "dribblesAttemptedAverage": "16.25/15.50",
        "dribblesAttemptedAverageHome": "18.25/17.50",
        "dribblesAttemptedAverageAway": "14.25/13.50"
    }
}