{
    "globalStatistics": {
        "corners": "5.29",
        "fouls": "12.86",
        "goalKicks": "7.11",
        "saves": "2.96",
        "offsides": "2.07",
        "shotsOnTarget": "5.39/4.07",
        "yellowCards": "2.04/2.21",
        "goals": "1.68/1.11",
        "throwIns": "20.57",
        "ballPossession": 54.571428571429,
        "tackles": "16.39/16.43",
        "interceptions": "8.82/7.61",
        "aerialDuels": "20.21",
        "aerialDuelsAttempted": "37.43",
        "dribbles": "6.93/8.43",
        "dribblesAttempted": "15.21/16.18"
    },
    "teamSlug": "sc-paderborn-07",
    "teamId": "2561",
    "teamName": "SC Paderborn 07",
    "tournament": "2. Bundesliga",
    "matchLinks": [
        {
            "href": "https://www.sofascore.com/football/match/sc-paderborn-07-spvgg-greuther-furth/bbbslbb#id:14065497,tab:statistics",
            "teams": [
                "SpVgg Greuther Fürth",
                "SC Paderborn 07"
            ],
            "goals": [
                0,
                2
            ],
            "teamIds": [
                2551,
                2561
            ],
            "isHome": false
        },
        {
            "href": "https://www.sofascore.com/football/match/sg-dynamo-dresden-sc-paderborn-07/lbbsVbb#id:14065485,tab:statistics",
            "teams": [
                "SC Paderborn 07",
                "SG Dynamo Dresden"
            ],
            "goals": [
                2,
                1
            ],
            "teamIds": [
                2561,
                2595
            ],
            "isHome": true
        },
        {
            "href": "https://www.sofascore.com/football/match/sc-paderborn-07-arminia-bielefeld/Pabslbb#id:14065477,tab:statistics",
            "teams": [
                "Arminia Bielefeld",
                "SC Paderborn 07"
            ],
            "goals": [
                2,
                2
            ],
            "teamIds": [
                2540,
                2561
            ],
            "isHome": false
        },
        {
            "href": "https://www.sofascore.com/football/match/sc-paderborn-07-eintracht-braunschweig/hbbslbb#id:14065466,tab:statistics",
            "teams": [
                "SC Paderborn 07",
                "Eintracht Braunschweig"
            ],
            "goals": [
                1,
                1
            ],
            "teamIds": [
                2561,
                2557
            ],
            "isHome": true
        },
        {
            "href": "https://www.sofascore.com/football/match/1-fc-kaiserslautern-sc-paderborn-07/lbbsAdb#id:14065458,tab:statistics",
            "teams": [
                "1. FC Kaiserslautern",
                "SC Paderborn 07"
            ],
            "goals": [
                1,
                2
            ],
            "teamIds": [
                2675,
                2561
            ],
            "isHome": false
        },
        {
            "href": "https://www.sofascore.com/football/match/sc-paderborn-07-hertha-bsc/Dabslbb#id:14065449,tab:statistics",
            "teams": [
                "SC Paderborn 07",
                "Hertha BSC"
            ],
            "goals": [
                5,
                2
            ],
            "teamIds": [
                2561,
                2528
            ],
            "isHome": true
        },
        {
            "href": "https://www.sofascore.com/football/match/sc-paderborn-07-vfl-bochum-1848/Rabslbb#id:14065441,tab:statistics",
            "teams": [
                "VfL Bochum 1848",
                "SC Paderborn 07"
            ],
            "goals": [
                0,
                0
            ],
            "teamIds": [
                2542,
                2561
            ],
            "isHome": false
        },
        {
            "href": "https://www.sofascore.com/football/match/sc-paderborn-07-1-fc-nurnberg/yabslbb#id:14065425,tab:statistics",
            "teams": [
                "SC Paderborn 07",
                "1. FC Nürnberg"
            ],
            "goals": [
                2,
                1
            ],
            "teamIds": [
                2561,
                2523
            ],
            "isHome": true
        }
    ],
    "homeMatchCount": 4,
    "awayMatchCount": 4,
    "matchStatistics": [
        {
            "corners": "4/3[A]",
            "fouls": "12/10[A]",
            "goalKicks": "11/10[A]",
            "saves": "3/2[A]",
            "offsides": "1/5[A]",
            "shotsOnTarget": "4/3[A]",
            "yellowCards": "3/1[A]",
            "goals": "2/0[A]",
            "throwIns": "15/20[A]",
            "averageBallPossession": "44/56[A]",
            "teams": "SC Paderborn 07,SpVgg Greuther Fürth,Away",
            "tackles": "13/11[A]",
            "interceptions": "10/5[A]",
            "aerialDuels": "11/15[A]",
            "aerialDuelsAttempted": "26/26[A]",
            "dribbles": "4/9[A]",
            "dribblesAttempted": "9/19[A]",
            "isHome": false
        },
        {
            "corners": "4/5[H]",
            "fouls": "9/8[H]",
            "goalKicks": "4/14[H]",
            "saves": "8/2[H]",
            "offsides": "1/1[H]",
            "shotsOnTarget": "4/8[H]",
            "yellowCards": "1/1[H]",
            "goals": "2/1[H]",
            "throwIns": "20/21[H]",
            "averageBallPossession": "53/47[H]",
            "teams": "SC Paderborn 07,SG Dynamo Dresden,Home",
            "tackles": "12/22[H]",
            "interceptions": "11/6[H]",
            "aerialDuels": "24/19[H]",
            "aerialDuelsAttempted": "43/43[H]",
            "dribbles": "8/7[H]",
            "dribblesAttempted": "17/15[H]",
            "isHome": true
        },
        {
            "corners": "1/4[A]",
            "fouls": "12/14[A]",
            "goalKicks": "9/4[A]",
            "saves": "5/2[A]",
            "offsides": "4/3[A]",
            "shotsOnTarget": "4/9[A]",
            "yellowCards": "2/3[A]",
            "goals": "2/2[A]",
            "throwIns": "22/19[A]",
            "averageBallPossession": "60/40[A]",
            "teams": "SC Paderborn 07,Arminia Bielefeld,Away",
            "tackles": "13/14[A]",
            "interceptions": "8/9[A]",
            "aerialDuels": "25/18[A]",
            "aerialDuelsAttempted": "43/43[A]",
            "dribbles": "8/11[A]",
            "dribblesAttempted": "12/17[A]",
            "isHome": false
        },
        {
            "corners": "9/5[H]",
            "fouls": "9/18[H]",
            "goalKicks": "2/9[H]",
            "saves": "2/3[H]",
            "offsides": "0/1[H]",
            "shotsOnTarget": "5/3[H]",
            "yellowCards": "1/2[H]",
            "goals": "1/1[H]",
            "throwIns": "21/10[H]",
            "averageBallPossession": "68/32[H]",
            "teams": "SC Paderborn 07,Eintracht Braunschweig,Home",
            "tackles": "12/11[H]",
            "interceptions": "2/6[H]",
            "aerialDuels": "28/23[H]",
            "aerialDuelsAttempted": "51/51[H]",
            "dribbles": "7/4[H]",
            "dribblesAttempted": "15/5[H]",
            "isHome": true
        },
        {
            "corners": "2/3[A]",
            "fouls": "24/12[A]",
            "goalKicks": "6/10[A]",
            "saves": "1/3[A]",
            "offsides": "0/5[A]",
            "shotsOnTarget": "5/2[A]",
            "yellowCards": "3/2[A]",
            "goals": "2/1[A]",
            "throwIns": "14/24[A]",
            "averageBallPossession": "52/48[A]",
            "teams": "SC Paderborn 07,1. FC Kaiserslautern,Away",
            "tackles": "18/20[A]",
            "interceptions": "9/7[A]",
            "aerialDuels": "23/26[A]",
            "aerialDuelsAttempted": "49/49[A]",
            "dribbles": "8/4[A]",
            "dribblesAttempted": "18/13[A]",
            "isHome": false
        },
        {
            "corners": "4/7[H]",
            "fouls": "9/15[H]",
            "goalKicks": "6/10[H]",
            "saves": "1/4[H]",
            "offsides": "3/4[H]",
            "shotsOnTarget": "9/3[H]",
            "yellowCards": "0/1[H]",
            "goals": "5/2[H]",
            "throwIns": "18/16[H]",
            "averageBallPossession": "54/46[H]",
            "teams": "SC Paderborn 07,Hertha BSC,Home",
            "tackles": "13/15[H]",
            "interceptions": "11/7[H]",
            "aerialDuels": "12/15[H]",
            "aerialDuelsAttempted": "27/27[H]",
            "dribbles": "7/15[H]",
            "dribblesAttempted": "16/22[H]",
            "isHome": true
        },
        {
            "corners": "6/4[A]",
            "fouls": "9/15[A]",
            "goalKicks": "12/6[A]",
            "saves": "10/3[A]",
            "offsides": "5/3[A]",
            "shotsOnTarget": "3/9[A]",
            "yellowCards": "3/2[A]",
            "goals": "0/0[A]",
            "throwIns": "17/23[A]",
            "averageBallPossession": "53/47[A]",
            "teams": "SC Paderborn 07,VfL Bochum 1848,Away",
            "tackles": "15/20[A]",
            "interceptions": "10/10[A]",
            "aerialDuels": "17/15[A]",
            "aerialDuelsAttempted": "32/32[A]",
            "dribbles": "10/10[A]",
            "dribblesAttempted": "20/16[A]",
            "isHome": false
        },
        {
            "corners": "6/5[H]",
            "fouls": "16/14[H]",
            "goalKicks": "5/10[H]",
            "saves": "2/5[H]",
            "offsides": "6/2[H]",
            "shotsOnTarget": "7/3[H]",
            "yellowCards": "2/3[H]",
            "goals": "2/1[H]",
            "throwIns": "22/27[H]",
            "averageBallPossession": "55/45[H]",
            "teams": "SC Paderborn 07,1. FC Nürnberg,Home",
            "tackles": "32/17[H]",
            "interceptions": "15/8[H]",
            "aerialDuels": "21/19[H]",
            "aerialDuelsAttempted": "40/40[H]",
            "dribbles": "9/9[H]",
            "dribblesAttempted": "19/22[H]",
            "isHome": true
        }
    ],
    "attempts": 0,
    "currentIndex": 7,
    "startTime": "2026-04-12T10:13:49.654Z",
    "endTime": "2026-04-12T10:14:18.037Z",
    "totalTimeSeconds": 28.38,
    "combinedMatchStatistics": {
        "corners": "4/3[A]+4/5[H]+1/4[A]+9/5[H]+2/3[A]+4/7[H]+6/4[A]+6/5[H]",
        "fouls": "12/10[A]+9/8[H]+12/14[A]+9/18[H]+24/12[A]+9/15[H]+9/15[A]+16/14[H]",
        "goalKicks": "11/10[A]+4/14[H]+9/4[A]+2/9[H]+6/10[A]+6/10[H]+12/6[A]+5/10[H]",
        "saves": "3/2[A]+8/2[H]+5/2[A]+2/3[H]+1/3[A]+1/4[H]+10/3[A]+2/5[H]",
        "offsides": "1/5[A]+1/1[H]+4/3[A]+0/1[H]+0/5[A]+3/4[H]+5/3[A]+6/2[H]",
        "shotsOnTarget": "4/3[A]+4/8[H]+4/9[A]+5/3[H]+5/2[A]+9/3[H]+3/9[A]+7/3[H]",
        "yellowCards": "3/1[A]+1/1[H]+2/3[A]+1/2[H]+3/2[A]+0/1[H]+3/2[A]+2/3[H]",
        "goals": "2/0[A]+2/1[H]+2/2[A]+1/1[H]+2/1[A]+5/2[H]+0/0[A]+2/1[H]",
        "throwIns": "15/20[A]+20/21[H]+22/19[A]+21/10[H]+14/24[A]+18/16[H]+17/23[A]+22/27[H]",
        "averageBallPossession": "44/56[A]+53/47[H]+60/40[A]+68/32[H]+52/48[A]+54/46[H]+53/47[A]+55/45[H]",
        "teams": "SC Paderborn 07,SpVgg Greuther Fürth,Away+SC Paderborn 07,SG Dynamo Dresden,Home+SC Paderborn 07,Arminia Bielefeld,Away+SC Paderborn 07,Eintracht Braunschweig,Home+SC Paderborn 07,1. FC Kaiserslautern,Away+SC Paderborn 07,Hertha BSC,Home+SC Paderborn 07,VfL Bochum 1848,Away+SC Paderborn 07,1. FC Nürnberg,Home",
        "tackles": "13/11[A]+12/22[H]+13/14[A]+12/11[H]+18/20[A]+13/15[H]+15/20[A]+32/17[H]",
        "interceptions": "10/5[A]+11/6[H]+8/9[A]+2/6[H]+9/7[A]+11/7[H]+10/10[A]+15/8[H]",
        "aerialDuels": "11/15[A]+24/19[H]+25/18[A]+28/23[H]+23/26[A]+12/15[H]+17/15[A]+21/19[H]",
        "aerialDuelsAttempted": "26/26[A]+43/43[H]+43/43[A]+51/51[H]+49/49[A]+27/27[H]+32/32[A]+40/40[H]",
        "dribbles": "4/9[A]+8/7[H]+8/11[A]+7/4[H]+8/4[A]+7/15[H]+10/10[A]+9/9[H]",
        "dribblesAttempted": "9/19[A]+17/15[H]+12/17[A]+15/5[H]+18/13[A]+16/22[H]+20/16[A]+19/22[H]",
        "isHome": "false+true+false+true+false+true+false+true",
        "cornersTotals": "36/36",
        "cornersTotalsHome": "23/22",
        "cornersTotalsAway": "13/14",
        "cornersAverage": "4.50/4.50",
        "cornersAverageHome": "5.75/5.50",
        "cornersAverageAway": "3.25/3.50",
        "foulsTotals": "100/106",
        "foulsTotalsHome": "43/55",
        "foulsTotalsAway": "57/51",
        "foulsAverage": "12.50/13.25",
        "foulsAverageHome": "10.75/13.75",
        "foulsAverageAway": "14.25/12.75",
        "goalKicksTotals": "55/73",
        "goalKicksTotalsHome": "17/43",
        "goalKicksTotalsAway": "38/30",
        "goalKicksAverage": "6.88/9.13",
        "goalKicksAverageHome": "4.25/10.75",
        "goalKicksAverageAway": "9.50/7.50",
        "savesTotals": "32/24",
        "savesTotalsHome": "13/14",
        "savesTotalsAway": "19/10",
        "savesAverage": "4.00/3.00",
        "savesAverageHome": "3.25/3.50",
        "savesAverageAway": "4.75/2.50",
        "offsidesTotals": "20/24",
        "offsidesTotalsHome": "10/8",
        "offsidesTotalsAway": "10/16",
        "offsidesAverage": "2.50/3.00",
        "offsidesAverageHome": "2.50/2.00",
        "offsidesAverageAway": "2.50/4.00",
        "shotsOnTargetTotals": "41/40",
        "shotsOnTargetTotalsHome": "25/17",
        "shotsOnTargetTotalsAway": "16/23",
        "shotsOnTargetAverage": "5.13/5.00",
        "shotsOnTargetAverageHome": "6.25/4.25",
        "shotsOnTargetAverageAway": "4.00/5.75",
        "yellowCardsTotals": "15/15",
        "yellowCardsTotalsHome": "4/7",
        "yellowCardsTotalsAway": "11/8",
        "yellowCardsAverage": "1.88/1.88",
        "yellowCardsAverageHome": "1.00/1.75",
        "yellowCardsAverageAway": "2.75/2.00",
        "goalsTotals": "16/8",
        "goalsTotalsHome": "10/5",
        "goalsTotalsAway": "6/3",
        "goalsAverage": "2.00/1.00",
        "goalsAverageHome": "2.50/1.25",
        "goalsAverageAway": "1.50/0.75",
        "throwInsTotals": "149/160",
        "throwInsTotalsHome": "81/74",
        "throwInsTotalsAway": "68/86",
        "throwInsAverage": "18.63/20.00",
        "throwInsAverageHome": "20.25/18.50",
        "throwInsAverageAway": "17.00/21.50",
        "averageBallPossessionTotals": "439/361",
        "averageBallPossessionTotalsHome": "230/170",
        "averageBallPossessionTotalsAway": "209/191",
        "averageBallPossessionAverage": "54.88/45.13",
        "averageBallPossessionAverageHome": "57.50/42.50",
        "averageBallPossessionAverageAway": "52.25/47.75",
        "tacklesTotals": "128/130",
        "tacklesTotalsHome": "69/65",
        "tacklesTotalsAway": "59/65",
        "tacklesAverage": "16.00/16.25",
        "tacklesAverageHome": "17.25/16.25",
        "tacklesAverageAway": "14.75/16.25",
        "interceptionsTotals": "76/58",
        "interceptionsTotalsHome": "39/27",
        "interceptionsTotalsAway": "37/31",
        "interceptionsAverage": "9.50/7.25",
        "interceptionsAverageHome": "9.75/6.75",
        "interceptionsAverageAway": "9.25/7.75",
        "aerialDuelsTotals": "161/150",
        "aerialDuelsTotalsHome": "85/76",
        "aerialDuelsTotalsAway": "76/74",
        "aerialDuelsAverage": "20.13/18.75",
        "aerialDuelsAverageHome": "21.25/19.00",
        "aerialDuelsAverageAway": "19.00/18.50",
        "aerialDuelsAttemptedTotals": "311/311",
        "aerialDuelsAttemptedTotalsHome": "161/161",
        "aerialDuelsAttemptedTotalsAway": "150/150",
        "aerialDuelsAttemptedAverage": "38.88/38.88",
        "aerialDuelsAttemptedAverageHome": "40.25/40.25",
        "aerialDuelsAttemptedAverageAway": "37.50/37.50",
        "dribblesTotals": "61/69",
        "dribblesTotalsHome": "31/35",
        "dribblesTotalsAway": "30/34",
        "dribblesAverage": "7.63/8.63",
        "dribblesAverageHome": "7.75/8.75",
        "dribblesAverageAway": "7.50/8.50",
        "dribblesAttemptedTotals": "126/129",
        "dribblesAttemptedTotalsHome": "67/64",
        "dribblesAttemptedTotalsAway": "59/65",
        "dribblesAttemptedAverage": "15.75/16.13",
        "dribblesAttemptedAverageHome": "16.75/16.00",
        "dribblesAttemptedAverageAway": "14.75/16.25"
    }
}